odoo10_addon_product_margin_classification-10.0.2.0.2-py3.8-nspkg.pth
odoo/addons/product_margin_classification/README.rst
odoo/addons/product_margin_classification/__init__.py
odoo/addons/product_margin_classification/__manifest__.py
odoo/addons/product_margin_classification/data/decimal_precision.xml
odoo/addons/product_margin_classification/demo/product_margin_classification.xml
odoo/addons/product_margin_classification/demo/product_template.xml
odoo/addons/product_margin_classification/demo/res_groups.xml
odoo/addons/product_margin_classification/i18n/am.po
odoo/addons/product_margin_classification/i18n/ar.po
odoo/addons/product_margin_classification/i18n/bg.po
odoo/addons/product_margin_classification/i18n/bs.po
odoo/addons/product_margin_classification/i18n/ca.po
odoo/addons/product_margin_classification/i18n/ca_ES.po
odoo/addons/product_margin_classification/i18n/cs.po
odoo/addons/product_margin_classification/i18n/da.po
odoo/addons/product_margin_classification/i18n/de.po
odoo/addons/product_margin_classification/i18n/el_GR.po
odoo/addons/product_margin_classification/i18n/en_GB.po
odoo/addons/product_margin_classification/i18n/es.po
odoo/addons/product_margin_classification/i18n/es_AR.po
odoo/addons/product_margin_classification/i18n/es_CL.po
odoo/addons/product_margin_classification/i18n/es_CO.po
odoo/addons/product_margin_classification/i18n/es_CR.po
odoo/addons/product_margin_classification/i18n/es_DO.po
odoo/addons/product_margin_classification/i18n/es_EC.po
odoo/addons/product_margin_classification/i18n/es_ES.po
odoo/addons/product_margin_classification/i18n/es_MX.po
odoo/addons/product_margin_classification/i18n/es_PE.po
odoo/addons/product_margin_classification/i18n/es_PY.po
odoo/addons/product_margin_classification/i18n/es_VE.po
odoo/addons/product_margin_classification/i18n/et.po
odoo/addons/product_margin_classification/i18n/fa.po
odoo/addons/product_margin_classification/i18n/fi.po
odoo/addons/product_margin_classification/i18n/fr.po
odoo10_addon_product_margin_classification-10.0.2.0.2.dist-info/METADATA
odoo10_addon_product_margin_classification-10.0.2.0.2.dist-info/WHEEL
odoo10_addon_product_margin_classification-10.0.2.0.2.dist-info/namespace_packages.txt
odoo10_addon_product_margin_classification-10.0.2.0.2.dist-info/top_level.txt
odoo10_addon_product_margin_classification-10.0.2.0.2.dist-info/RECORD
